askcomm/__init__.py
askcomm/askcomm.py
askcomm-0.0.2.dist-info/LICENSE
askcomm-0.0.2.dist-info/METADATA
askcomm-0.0.2.dist-info/WHEEL
askcomm-0.0.2.dist-info/top_level.txt
askcomm-0.0.2.dist-info/RECORD
