Metadata-Version: 2.1
Name: askcomm
Version: 0.0.2
Summary: A set of search patterns that query a corpus of event-based and community-detected tweets, but it could be modified to query most social-network (node-edge) data.
Home-page: https://github.com/lingeringcode/askcomm/
Author: Chris A. Lindgren
Author-email: chris.a.lindgren@gmail.com
License: UNKNOWN
Download-URL: https://github.com/lingeringcode/askcomm/
Keywords: corpus querying,search patterns,event-based corpus
Platform: UNKNOWN
Requires-Dist: pandas
Requires-Dist: tqdm
